data/__init__.py
pybullet_suite/__init__.py
pybullet_suite/assets/__init__.py
pybullet_suite/assets/__pycache__/__init__.cpython-38.pyc
pybullet_suite/assets/urdfs/panda/LICENSE.txt
pybullet_suite/assets/urdfs/panda/__init__.py
pybullet_suite/assets/urdfs/panda/franka_panda.urdf
pybullet_suite/assets/urdfs/panda/hand.urdf
pybullet_suite/assets/urdfs/panda/panda_hand.urdf
pybullet_suite/assets/urdfs/panda/meshes/collision/finger.obj
pybullet_suite/assets/urdfs/panda/meshes/collision/hand.obj
pybullet_suite/assets/urdfs/panda/meshes/collision/link0.obj
pybullet_suite/assets/urdfs/panda/meshes/collision/link1.obj
pybullet_suite/assets/urdfs/panda/meshes/collision/link2.obj
pybullet_suite/assets/urdfs/panda/meshes/collision/link3.obj
pybullet_suite/assets/urdfs/panda/meshes/collision/link4.obj
pybullet_suite/assets/urdfs/panda/meshes/collision/link5.obj
pybullet_suite/assets/urdfs/panda/meshes/collision/link6.mtl
pybullet_suite/assets/urdfs/panda/meshes/collision/link6.obj
pybullet_suite/assets/urdfs/panda/meshes/collision/link7.obj
pybullet_suite/assets/urdfs/panda/meshes/visual/colors.png
pybullet_suite/assets/urdfs/panda/meshes/visual/finger.mtl
pybullet_suite/assets/urdfs/panda/meshes/visual/finger.obj
pybullet_suite/assets/urdfs/panda/meshes/visual/hand.mtl
pybullet_suite/assets/urdfs/panda/meshes/visual/hand.obj
pybullet_suite/assets/urdfs/panda/meshes/visual/link1.mtl
pybullet_suite/assets/urdfs/panda/meshes/visual/link1.obj
pybullet_suite/assets/urdfs/panda/meshes/visual/link2.mtl
pybullet_suite/assets/urdfs/panda/meshes/visual/link2.obj
pybullet_suite/assets/urdfs/panda/meshes/visual/link3.mtl
pybullet_suite/assets/urdfs/panda/meshes/visual/link3.obj
pybullet_suite/assets/urdfs/panda/meshes/visual/link4.mtl
pybullet_suite/assets/urdfs/panda/meshes/visual/link4.obj
pybullet_suite/assets/urdfs/panda/meshes/visual/link5.mtl
pybullet_suite/assets/urdfs/panda/meshes/visual/link5.obj
pybullet_suite/assets/urdfs/panda/meshes/visual/link6.mtl
pybullet_suite-0.0.13.dist-info/METADATA
pybullet_suite-0.0.13.dist-info/WHEEL
pybullet_suite-0.0.13.dist-info/top_level.txt
pybullet_suite-0.0.13.dist-info/RECORD
